{"data":{"monitors":[{"locationStop":{"type":"Feature","geometry":{"type":"Point","coordinates":[16.3916039,48.2182083]},"properties":{"name":"60201040","title":"Praterstern S U","municipality":"Wien","municipalityId":49000001,"type":"stop","coordName":"WGS84","attributes":{"rbl":345}}},"lines":[{"name":"5","towards":"Westbahnhof S U","direction":"H","platform":"1","richtungsId":"1","barrierFree":true,"realtimeSupported":true,"trafficjam":false,"departures":{"departure":[{"departureTime":{"timePlanned":"2025-05-21T09:24:30.000+0200","timeReal":"2025-05-21T09:26:34.000+0200","countdown":0},"vehicle":{"name":"5","towards":"Westbahnhof S U","direction":"H","platform":"1","richtungsId":"1","barrierFree":true,"foldingRamp":false,"realtimeSupported":true,"trafficjam":false,"type":"ptTram","attributes":{},"linienId":105}},{"departureTime":{"timePlanned":"2025-05-21T09:32:00.000+0200","timeReal":"2025-05-21T09:32:00.000+0200","countdown":5},"vehicle":{"name":"5","towards":"Westbahnhof S U","direction":"H","platform":"1","richtungsId":"1","barrierFree":true,"foldingRamp":false,"realtimeSupported":true,"trafficjam":false,"type":"ptTram","attributes":{},"linienId":105}},{"departureTime":{"timePlanned":"2025-05-21T09:39:30.000+0200","timeReal":"2025-05-21T09:39:30.000+0200","countdown":13},"vehicle":{"name":"5","towards":"Westbahnhof S U","direction":"H","platform":"1","richtungsId":"1","barrierFree":true,"foldingRamp":false,"realtimeSupported":true,"trafficjam":false,"type":"ptTram","attributes":{},"linienId":105}},{"departureTime":{"timePlanned":"2025-05-21T09:47:00.000+0200","timeReal":"2025-05-21T09:47:00.000+0200","countdown":20},"vehicle":{"name":"5","towards":"Westbahnhof S U","direction":"H","platform":"1","richtungsId":"1","barrierFree":true,"foldingRamp":false,"realtimeSupported":true,"trafficjam":false,"type":"ptTram","attributes":{},"linienId":105}},{"departureTime":{"timePlanned":"2025-05-21T09:54:30.000+0200","timeReal":"2025-05-21T09:54:30.000+0200","countdown":28},"vehicle":{"name":"5","towards":"Westbahnhof S U","direction":"H","platform":"1","richtungsId":"1","barrierFree":true,"foldingRamp":false,"realtimeSupported":true,"trafficjam":false,"type":"ptTram","attributes":{},"linienId":105}},{"departureTime":{"timePlanned":"2025-05-21T10:02:00.000+0200","timeReal":"2025-05-21T10:02:00.000+0200","countdown":35},"vehicle":{"name":"5","towards":"Westbahnhof S U","direction":"H","platform":"1","richtungsId":"1","barrierFree":true,"foldingRamp":false,"realtimeSupported":true,"trafficjam":false,"type":"ptTram","attributes":{},"linienId":105}},{"departureTime":{"timePlanned":"2025-05-21T10:09:30.000+0200","timeReal":"2025-05-21T10:09:30.000+0200","countdown":43},"vehicle":{"name":"5","towards":"Westbahnhof S U","direction":"H","platform":"1","richtungsId":"1","barrierFree":true,"foldingRamp":false,"realtimeSupported":true,"trafficjam":false,"type":"ptTram","attributes":{},"linienId":105}},{"departureTime":{"timePlanned":"2025-05-21T10:17:00.000+0200","timeReal":"2025-05-21T10:17:00.000+0200","countdown":50},"vehicle":{"name":"5","towards":"Westbahnhof S U","direction":"H","platform":"1","richtungsId":"1","barrierFree":true,"foldingRamp":false,"realtimeSupported":true,"trafficjam":false,"type":"ptTram","attributes":{},"linienId":105}},{"departureTime":{"timePlanned":"2025-05-21T10:24:30.000+0200","timeReal":"2025-05-21T10:24:30.000+0200","countdown":58},"vehicle":{"name":"5","towards":"Westbahnhof S U","direction":"H","platform":"1","richtungsId":"1","barrierFree":true,"foldingRamp":false,"realtimeSupported":true,"trafficjam":false,"type":"ptTram","attributes":{},"linienId":105}},{"departureTime":{"timePlanned":"2025-05-21T10:32:00.000+0200","timeReal":"2025-05-21T10:32:00.000+0200","countdown":65},"vehicle":{"name":"5","towards":"Westbahnhof S U","direction":"H","platform":"1","richtungsId":"1","barrierFree":true,"foldingRamp":false,"realtimeSupported":true,"trafficjam":false,"type":"ptTram","attributes":{},"linienId":105}}]},"type":"ptTram","lineId":105}],"attributes":{}},{"locationStop":{"type":"Feature","geometry":{"type":"Point","coordinates":[16.3916039,48.2181784]},"properties":{"name":"60201040","title":"Praterstern S U","municipality":"Wien","municipalityId":49000001,"type":"stop","coordName":"WGS84","attributes":{"rbl":2100}}},"lines":[{"name":"5B","towards":"Bhf. Heiligenstadt S U","direction":"H","platform":"1","richtungsId":"1","barrierFree":true,"realtimeSupported":true,"trafficjam":false,"departures":{"departure":[{"departureTime":{"timePlanned":"2025-05-21T09:31:00.000+0200","timeReal":"2025-05-21T09:31:00.000+0200","countdown":4},"vehicle":{"name":"5B","towards":"Bhf. Heiligenstadt S U","direction":"H","platform":"1","richtungsId":"1","barrierFree":true,"foldingRamp":false,"realtimeSupported":true,"trafficjam":false,"type":"ptBusCity","attributes":{},"linienId":205}},{"departureTime":{"timePlanned":"2025-05-21T09:41:00.000+0200","timeReal":"2025-05-21T09:41:00.000+0200","countdown":14},"vehicle":{"name":"5B","towards":"Bhf. Heiligenstadt S U","direction":"H","platform":"1","richtungsId":"1","barrierFree":true,"foldingRamp":false,"realtimeSupported":true,"trafficjam":false,"type":"ptBusCity","attributes":{},"linienId":205}},{"departureTime":{"timePlanned":"2025-05-21T09:51:00.000+0200","timeReal":"2025-05-21T09:51:00.000+0200","countdown":24},"vehicle":{"name":"5B","towards":"Bhf. Heiligenstadt S U","direction":"H","platform":"1","richtungsId":"1","barrierFree":true,"foldingRamp":false,"realtimeSupported":true,"trafficjam":false,"type":"ptBusCity","attributes":{},"linienId":205}},{"departureTime":{"timePlanned":"2025-05-21T10:01:00.000+0200","timeReal":"2025-05-21T10:01:00.000+0200","countdown":34},"vehicle":{"name":"5B","towards":"Bhf. Heiligenstadt S U","direction":"H","platform":"1","richtungsId":"1","barrierFree":true,"foldingRamp":false,"realtimeSupported":true,"trafficjam":false,"type":"ptBusCity","attributes":{},"linienId":205}},{"departureTime":{"timePlanned":"2025-05-21T10:11:00.000+0200","timeReal":"2025-05-21T10:11:00.000+0200","countdown":44},"vehicle":{"name":"5B","towards":"Bhf. Heiligenstadt S U","direction":"H","platform":"1","richtungsId":"1","barrierFree":true,"foldingRamp":false,"realtimeSupported":true,"trafficjam":false,"type":"ptBusCity","attributes":{},"linienId":205}},{"departureTime":{"timePlanned":"2025-05-21T10:21:00.000+0200","timeReal":"2025-05-21T10:21:00.000+0200","countdown":54},"vehicle":{"name":"5B","towards":"Bhf. Heiligenstadt S U","direction":"H","platform":"1","richtungsId":"1","barrierFree":true,"foldingRamp":false,"realtimeSupported":true,"trafficjam":false,"type":"ptBusCity","attributes":{},"linienId":205}},{"departureTime":{"timePlanned":"2025-05-21T10:31:00.000+0200","timeReal":"2025-05-21T10:31:00.000+0200","countdown":64},"vehicle":{"name":"5B","towards":"Bhf. Heiligenstadt S U","direction":"H","platform":"1","richtungsId":"1","barrierFree":true,"foldingRamp":false,"realtimeSupported":true,"trafficjam":false,"type":"ptBusCity","attributes":{},"linienId":205}}]},"type":"ptBusCity","lineId":205}],"attributes":{}},{"locationStop":{"type":"Feature","geometry":{"type":"Point","coordinates":[16.391532,48.2181724]},"properties":{"name":"60201040","title":"Praterstern SU","municipality":"Wien","municipalityId":49000001,"type":"stop","coordName":"WGS84","attributes":{"rbl":3886}}},"lines":[{"name":"80A","towards":"Neu Marx","direction":"H","platform":"1","richtungsId":"1","barrierFree":true,"realtimeSupported":true,"trafficjam":false,"departures":{"departure":[{"departureTime":{"timePlanned":"2025-05-21T09:28:00.000+0200","timeReal":"2025-05-21T09:28:00.000+0200","countdown":1},"vehicle":{"name":"80A","towards":"Neu Marx","direction":"H","platform":"1","richtungsId":"1","barrierFree":true,"foldingRamp":false,"realtimeSupported":true,"trafficjam":false,"type":"ptBusCity","attributes":{},"linienId":480}},{"departureTime":{"timePlanned":"2025-05-21T09:38:00.000+0200","timeReal":"2025-05-21T09:38:00.000+0200","countdown":11},"vehicle":{"name":"80A","towards":"Neu Marx","direction":"H","platform":"1","richtungsId":"1","barrierFree":true,"foldingRamp":false,"realtimeSupported":true,"trafficjam":false,"type":"ptBusCity","attributes":{},"linienId":480}},{"departureTime":{"timePlanned":"2025-05-21T09:48:00.000+0200","timeReal":"2025-05-21T09:48:00.000+0200","countdown":21},"vehicle":{"name":"80A","towards":"Neu Marx","direction":"H","platform":"1","richtungsId":"1","barrierFree":true,"foldingRamp":false,"realtimeSupported":true,"trafficjam":false,"type":"ptBusCity","attributes":{},"linienId":480}},{"departureTime":{"timePlanned":"2025-05-21T09:58:00.000+0200","timeReal":"2025-05-21T09:58:00.000+0200","countdown":31},"vehicle":{"name":"80A","towards":"Neu Marx","direction":"H","platform":"1","richtungsId":"1","barrierFree":true,"foldingRamp":false,"realtimeSupported":true,"trafficjam":false,"type":"ptBusCity","attributes":{},"linienId":480}},{"departureTime":{"timePlanned":"2025-05-21T10:08:00.000+0200","timeReal":"2025-05-21T10:08:00.000+0200","countdown":41},"vehicle":{"name":"80A","towards":"Neu Marx","direction":"H","platform":"1","richtungsId":"1","barrierFree":true,"foldingRamp":false,"realtimeSupported":true,"trafficjam":false,"type":"ptBusCity","attributes":{},"linienId":480}},{"departureTime":{"timePlanned":"2025-05-21T10:18:00.000+0200","timeReal":"2025-05-21T10:18:00.000+0200","countdown":51},"vehicle":{"name":"80A","towards":"Neu Marx","direction":"H","platform":"1","richtungsId":"1","barrierFree":true,"foldingRamp":false,"realtimeSupported":true,"trafficjam":false,"type":"ptBusCity","attributes":{},"linienId":480}},{"departureTime":{"timePlanned":"2025-05-21T10:28:00.000+0200","timeReal":"2025-05-21T10:28:00.000+0200","countdown":61},"vehicle":{"name":"80A","towards":"Neu Marx","direction":"H","platform":"1","richtungsId":"1","barrierFree":true,"foldingRamp":false,"realtimeSupported":true,"trafficjam":false,"type":"ptBusCity","attributes":{},"linienId":480}}]},"type":"ptBusCity","lineId":480}],"attributes":{}},{"locationStop":{"type":"Feature","geometry":{"type":"Point","coordinates":[16.3932478,48.2200518]},"properties":{"name":"60201040","title":"Praterstern S U","municipality":"Wien","municipalityId":49000001,"type":"stop","coordName":"WGS84","gate":"D","attributes":{"rbl":2704}}},"lines":[{"name":"82A","towards":"Krieau U","direction":"H","platform":"1","richtungsId":"1","barrierFree":true,"realtimeSupported":true,"trafficjam":false,"departures":{"departure":[{"departureTime":{"timePlanned":"2025-05-21T09:27:00.000+0200","timeReal":"2025-05-21T09:27:00.000+0200","countdown":0},"vehicle":{"name":"82A","towards":"Krieau U","direction":"H","platform":"1","richtungsId":"1","barrierFree":true,"foldingRamp":false,"realtimeSupported":true,"trafficjam":false,"type":"ptBusCity","attributes":{},"linienId":482}},{"departureTime":{"timePlanned":"2025-05-21T09:42:00.000+0200","timeReal":"2025-05-21T09:42:00.000+0200","countdown":15},"vehicle":{"name":"82A","towards":"Krieau U","direction":"H","platform":"1","richtungsId":"1","barrierFree":true,"foldingRamp":false,"realtimeSupported":true,"trafficjam":false,"type":"ptBusCity","attributes":{},"linienId":482}},{"departureTime":{"timePlanned":"2025-05-21T09:57:00.000+0200","timeReal":"2025-05-21T09:57:00.000+0200","countdown":30},"vehicle":{"name":"82A","towards":"Krieau U","direction":"H","platform":"1","richtungsId":"1","barrierFree":true,"foldingRamp":false,"realtimeSupported":true,"trafficjam":false,"type":"ptBusCity","attributes":{},"linienId":482}},{"departureTime":{"timePlanned":"2025-05-21T10:12:00.000+0200","timeReal":"2025-05-21T10:12:00.000+0200","countdown":45},"vehicle":{"name":"82A","towards":"Krieau U","direction":"H","platform":"1","richtungsId":"1","barrierFree":true,"foldingRamp":false,"realtimeSupported":true,"trafficjam":false,"type":"ptBusCity","attributes":{},"linienId":482}},{"departureTime":{"timePlanned":"2025-05-21T10:27:00.000+0200","timeReal":"2025-05-21T10:27:00.000+0200","countdown":60},"vehicle":{"name":"82A","towards":"Krieau U","direction":"H","platform":"1","richtungsId":"1","barrierFree":true,"foldingRamp":false,"realtimeSupported":true,"trafficjam":false,"type":"ptBusCity","attributes":{},"linienId":482}}]},"type":"ptBusCity","lineId":482}],"attributes":{}},{"locationStop":{"type":"Feature","geometry":{"type":"Point","coordinates":[16.3916039,48.2183579]},"properties":{"name":"60201040","title":"Praterstern S U","municipality":"Wien","municipalityId":49000001,"type":"stop","coordName":"WGS84","attributes":{"rbl":311}}},"lines":[{"name":"O","towards":"Bruno-Marek-Allee","direction":"H","platform":"1","richtungsId":"1","barrierFree":true,"realtimeSupported":true,"trafficjam":false,"departures":{"departure":[{"departureTime":{"timePlanned":"2025-05-21T09:29:00.000+0200","timeReal":"2025-05-21T09:31:27.000+0200","countdown":5},"vehicle":{"name":"O","towards":"Bruno-Marek-Allee","direction":"H","platform":"1","richtungsId":"1","barrierFree":true,"foldingRamp":false,"realtimeSupported":true,"trafficjam":false,"type":"ptTram","attributes":{},"linienId":170}},{"departureTime":{"timePlanned":"2025-05-21T09:35:00.000+0200","timeReal":"2025-05-21T09:39:44.000+0200","countdown":13},"vehicle":{"name":"O","towards":"Bruno-Marek-Allee","direction":"H","platform":"1","richtungsId":"1","barrierFree":true,"foldingRamp":false,"realtimeSupported":true,"trafficjam":false,"type":"ptTram","attributes":{},"linienId":170}},{"departureTime":{"timePlanned":"2025-05-21T09:41:00.000+0200","timeReal":"2025-05-21T09:43:54.000+0200","countdown":17},"vehicle":{"name":"O","towards":"Bruno-Marek-Allee","direction":"H","platform":"1","richtungsId":"1","barrierFree":true,"foldingRamp":false,"realtimeSupported":true,"trafficjam":false,"type":"ptTram","attributes":{},"linienId":170}},{"departureTime":{"timePlanned":"2025-05-21T09:47:40.000+0200","timeReal":"2025-05-21T09:49:00.000+0200","countdown":22},"vehicle":{"name":"O","towards":"Bruno-Marek-Allee","direction":"H","platform":"1","richtungsId":"1","barrierFree":true,"foldingRamp":false,"realtimeSupported":true,"trafficjam":false,"type":"ptTram","attributes":{},"linienId":170}},{"departureTime":{"timePlanned":"2025-05-21T09:54:20.000+0200","timeReal":"2025-05-21T09:53:20.000+0200","countdown":27},"vehicle":{"name":"O","towards":"Bruno-Marek-Allee","direction":"H","platform":"1","richtungsId":"1","barrierFree":true,"foldingRamp":false,"realtimeSupported":true,"trafficjam":false,"type":"ptTram","attributes":{},"linienId":170}},{"departureTime":{"timePlanned":"2025-05-21T10:01:00.000+0200","timeReal":"2025-05-21T10:01:00.000+0200","countdown":34},"vehicle":{"name":"O","towards":"Bruno-Marek-Allee","direction":"H","platform":"1","richtungsId":"1","barrierFree":true,"foldingRamp":false,"realtimeSupported":true,"trafficjam":false,"type":"ptTram","attributes":{},"linienId":170}},{"departureTime":{"timePlanned":"2025-05-21T10:07:40.000+0200","timeReal":"2025-05-21T10:07:40.000+0200","countdown":41},"vehicle":{"name":"O","towards":"Bruno-Marek-Allee","direction":"H","platform":"1","richtungsId":"1","barrierFree":true,"foldingRamp":false,"realtimeSupported":true,"trafficjam":false,"type":"ptTram","attributes":{},"linienId":170}},{"departureTime":{"timePlanned":"2025-05-21T10:14:20.000+0200","timeReal":"2025-05-21T10:14:20.000+0200","countdown":48},"vehicle":{"name":"O","towards":"Bruno-Marek-Allee","direction":"H","platform":"1","richtungsId":"1","barrierFree":true,"foldingRamp":false,"realtimeSupported":true,"trafficjam":false,"type":"ptTram","attributes":{},"linienId":170}},{"departureTime":{"timePlanned":"2025-05-21T10:21:00.000+0200","timeReal":"2025-05-21T10:21:00.000+0200","countdown":54},"vehicle":{"name":"O","towards":"Bruno-Marek-Allee","direction":"H","platform":"1","richtungsId":"1","barrierFree":true,"foldingRamp":false,"realtimeSupported":true,"trafficjam":false,"type":"ptTram","attributes":{},"linienId":170}},{"departureTime":{"timePlanned":"2025-05-21T10:27:40.000+0200","timeReal":"2025-05-21T10:27:40.000+0200","countdown":61},"vehicle":{"name":"O","towards":"Bruno-Marek-Allee","direction":"H","platform":"1","richtungsId":"1","barrierFree":true,"foldingRamp":false,"realtimeSupported":true,"trafficjam":false,"type":"ptTram","attributes":{},"linienId":170}},{"departureTime":{"timePlanned":"2025-05-21T10:35:30.000+0200","timeReal":"2025-05-21T10:35:30.000+0200","countdown":69},"vehicle":{"name":"O","towards":"Bruno-Marek-Allee","direction":"H","platform":"1","richtungsId":"1","barrierFree":true,"foldingRamp":false,"realtimeSupported":true,"trafficjam":false,"type":"ptTram","attributes":{},"linienId":170}}]},"type":"ptTram","lineId":170}],"attributes":{}},{"locationStop":{"type":"Feature","geometry":{"type":"Point","coordinates":[16.3913614,48.2182682]},"properties":{"name":"60201040","title":"Praterstern","municipality":"Wien","municipalityId":49000001,"type":"stop","coordName":"WGS84","attributes":{"rbl":3450}}},"lines":[{"name":"O","towards":"Raxstraße, Rudolfshügelgasse","direction":"R","platform":"2","richtungsId":"2","barrierFree":true,"realtimeSupported":true,"trafficjam":false,"departures":{"departure":[{"departureTime":{"timePlanned":"2025-05-21T09:28:00.000+0200","timeReal":"2025-05-21T09:26:05.000+0200","countdown":0},"vehicle":{"name":"O","towards":"Raxstraße, Rudolfshügelgasse","direction":"R","platform":"2","richtungsId":"2","barrierFree":true,"foldingRamp":false,"realtimeSupported":true,"trafficjam":false,"type":"ptTram","attributes":{},"linienId":170}},{"departureTime":{"timePlanned":"2025-05-21T09:34:40.000+0200","timeReal":"2025-05-21T09:34:40.000+0200","countdown":8},"vehicle":{"name":"O","towards":"Raxstraße, Rudolfshügelgasse","direction":"R","platform":"2","richtungsId":"2","barrierFree":true,"foldingRamp":false,"realtimeSupported":true,"trafficjam":false,"type":"ptTram","attributes":{},"linienId":170}},{"departureTime":{"timePlanned":"2025-05-21T09:41:20.000+0200","timeReal":"2025-05-21T09:41:20.000+0200","countdown":15},"vehicle":{"name":"O","towards":"Raxstraße, Rudolfshügelgasse","direction":"R","platform":"2","richtungsId":"2","barrierFree":true,"foldingRamp":false,"realtimeSupported":true,"trafficjam":false,"type":"ptTram","attributes":{},"linienId":170}},{"departureTime":{"timePlanned":"2025-05-21T09:48:00.000+0200","timeReal":"2025-05-21T09:48:00.000+0200","countdown":21},"vehicle":{"name":"O","towards":"Raxstraße, Rudolfshügelgasse","direction":"R","platform":"2","richtungsId":"2","barrierFree":true,"foldingRamp":false,"realtimeSupported":true,"trafficjam":false,"type":"ptTram","attributes":{},"linienId":170}},{"departureTime":{"timePlanned":"2025-05-21T09:54:40.000+0200","timeReal":"2025-05-21T09:54:40.000+0200","countdown":28},"vehicle":{"name":"O","towards":"Raxstraße, Rudolfshügelgasse","direction":"R","platform":"2","richtungsId":"2","barrierFree":true,"foldingRamp":false,"realtimeSupported":true,"trafficjam":false,"type":"ptTram","attributes":{},"linienId":170}},{"departureTime":{"timePlanned":"2025-05-21T10:01:20.000+0200","timeReal":"2025-05-21T10:01:20.000+0200","countdown":35},"vehicle":{"name":"O","towards":"Raxstraße, Rudolfshügelgasse","direction":"R","platform":"2","richtungsId":"2","barrierFree":true,"foldingRamp":false,"realtimeSupported":true,"trafficjam":false,"type":"ptTram","attributes":{},"linienId":170}},{"departureTime":{"timePlanned":"2025-05-21T10:08:00.000+0200","timeReal":"2025-05-21T10:08:00.000+0200","countdown":41},"vehicle":{"name":"O","towards":"Raxstraße, Rudolfshügelgasse","direction":"R","platform":"2","richtungsId":"2","barrierFree":true,"foldingRamp":false,"realtimeSupported":true,"trafficjam":false,"type":"ptTram","attributes":{},"linienId":170}},{"departureTime":{"timePlanned":"2025-05-21T10:14:40.000+0200","timeReal":"2025-05-21T10:14:40.000+0200","countdown":48},"vehicle":{"name":"O","towards":"Raxstraße, Rudolfshügelgasse","direction":"R","platform":"2","richtungsId":"2","barrierFree":true,"foldingRamp":false,"realtimeSupported":true,"trafficjam":false,"type":"ptTram","attributes":{},"linienId":170}},{"departureTime":{"timePlanned":"2025-05-21T10:21:20.000+0200","timeReal":"2025-05-21T10:21:20.000+0200","countdown":55},"vehicle":{"name":"O","towards":"Raxstraße, Rudolfshügelgasse","direction":"R","platform":"2","richtungsId":"2","barrierFree":true,"foldingRamp":false,"realtimeSupported":true,"trafficjam":false,"type":"ptTram","attributes":{},"linienId":170}},{"departureTime":{"timePlanned":"2025-05-21T10:28:00.000+0200","timeReal":"2025-05-21T10:28:00.000+0200","countdown":61},"vehicle":{"name":"O","towards":"Raxstraße, Rudolfshügelgasse","direction":"R","platform":"2","richtungsId":"2","barrierFree":true,"foldingRamp":false,"realtimeSupported":true,"trafficjam":false,"type":"ptTram","attributes":{},"linienId":170}},{"departureTime":{"timePlanned":"2025-05-21T10:34:40.000+0200","timeReal":"2025-05-21T10:34:40.000+0200","countdown":68},"vehicle":{"name":"O","towards":"Raxstraße, Rudolfshügelgasse","direction":"R","platform":"2","richtungsId":"2","barrierFree":true,"foldingRamp":false,"realtimeSupported":true,"trafficjam":false,"type":"ptTram","attributes":{},"linienId":170}}]},"type":"ptTram","lineId":170}],"attributes":{}},{"locationStop":{"type":"Feature","geometry":{"type":"Point","coordinates":[16.3916398,48.2190642]},"properties":{"name":"60201040","title":"Praterstern","municipality":"Wien","municipalityId":49000001,"type":"stop","coordName":"WGS84","gate":"1","attributes":{"rbl":4117}}},"lines":[{"name":"U1","towards":"LEOPOLDAU     ","direction":"H","platform":"1","richtungsId":"1","barrierFree":true,"realtimeSupported":true,"trafficjam":false,"departures":{"departure":[{"departureTime":{"timePlanned":"2025-05-21T09:29:09.000+0200","timeReal":"2025-05-21T09:29:09.000+0200","countdown":3},"vehicle":{"name":"U1","towards":"LEOPOLDAU     ","direction":"H","platform":"1","richtungsId":"1","barrierFree":true,"foldingRamp":true,"foldingRampType":"part","realtimeSupported":true,"trafficjam":false,"type":"ptMetro","attributes":{},"linienId":301}},{"departureTime":{"timePlanned":"2025-05-21T09:32:09.000+0200","timeReal":"2025-05-21T09:32:09.000+0200","countdown":6},"vehicle":{"name":"U1","towards":"LEOPOLDAU","direction":"H","platform":"1","richtungsId":"1","barrierFree":true,"realtimeSupported":true,"trafficjam":false,"type":"ptMetro","attributes":{},"linienId":301}},{"departureTime":{"timePlanned":"2025-05-21T09:36:15.000+0200","countdown":9},"vehicle":{"name":"U1","towards":"Leopoldau","direction":"H","platform":"1","richtungsId":"1","barrierFree":true,"foldingRamp":false,"realtimeSupported":true,"trafficjam":false,"type":"ptMetro","attributes":{},"linienId":301}},{"departureTime":{"timePlanned":"2025-05-21T09:40:00.000+0200","countdown":13},"vehicle":{"name":"U1","towards":"Leopoldau","direction":"H","platform":"1","richtungsId":"1","barrierFree":true,"foldingRamp":false,"realtimeSupported":true,"trafficjam":false,"type":"ptMetro","attributes":{},"linienId":301}},{"departureTime":{"timePlanned":"2025-05-21T09:43:45.000+0200","countdown":17},"vehicle":{"name":"U1","towards":"Leopoldau","direction":"H","platform":"1","richtungsId":"1","barrierFree":true,"foldingRamp":false,"realtimeSupported":true,"trafficjam":false,"type":"ptMetro","attributes":{},"linienId":301}},{"departureTime":{"timePlanned":"2025-05-21T09:47:30.000+0200","countdown":21},"vehicle":{"name":"U1","towards":"Leopoldau","direction":"H","platform":"1","richtungsId":"1","barrierFree":true,"foldingRamp":false,"realtimeSupported":true,"trafficjam":false,"type":"ptMetro","attributes":{},"linienId":301}},{"departureTime":{"timePlanned":"2025-05-21T09:51:15.000+0200","countdown":24},"vehicle":{"name":"U1","towards":"Leopoldau","direction":"H","platform":"1","richtungsId":"1","barrierFree":true,"foldingRamp":false,"realtimeSupported":true,"trafficjam":false,"type":"ptMetro","attributes":{},"linienId":301}},{"departureTime":{"timePlanned":"2025-05-21T09:55:00.000+0200","countdown":28},"vehicle":{"name":"U1","towards":"Leopoldau","direction":"H","platform":"1","richtungsId":"1","barrierFree":true,"foldingRamp":false,"realtimeSupported":true,"trafficjam":false,"type":"ptMetro","attributes":{},"linienId":301}},{"departureTime":{"timePlanned":"2025-05-21T09:58:45.000+0200","countdown":32},"vehicle":{"name":"U1","towards":"Leopoldau","direction":"H","platform":"1","richtungsId":"1","barrierFree":true,"foldingRamp":false,"realtimeSupported":true,"trafficjam":false,"type":"ptMetro","attributes":{},"linienId":301}},{"departureTime":{"timePlanned":"2025-05-21T10:02:30.000+0200","countdown":36},"vehicle":{"name":"U1","towards":"Leopoldau","direction":"H","platform":"1","richtungsId":"1","barrierFree":true,"foldingRamp":false,"realtimeSupported":true,"trafficjam":false,"type":"ptMetro","attributes":{},"linienId":301}},{"departureTime":{"timePlanned":"2025-05-21T10:06:15.000+0200","countdown":39},"vehicle":{"name":"U1","towards":"Leopoldau","direction":"H","platform":"1","richtungsId":"1","barrierFree":true,"foldingRamp":false,"realtimeSupported":true,"trafficjam":false,"type":"ptMetro","attributes":{},"linienId":301}},{"departureTime":{"timePlanned":"2025-05-21T10:10:00.000+0200","countdown":43},"vehicle":{"name":"U1","towards":"Leopoldau","direction":"H","platform":"1","richtungsId":"1","barrierFree":true,"foldingRamp":false,"realtimeSupported":true,"trafficjam":false,"type":"ptMetro","attributes":{},"linienId":301}},{"departureTime":{"timePlanned":"2025-05-21T10:13:45.000+0200","countdown":47},"vehicle":{"name":"U1","towards":"Leopoldau","direction":"H","platform":"1","richtungsId":"1","barrierFree":true,"foldingRamp":false,"realtimeSupported":true,"trafficjam":false,"type":"ptMetro","attributes":{},"linienId":301}},{"departureTime":{"timePlanned":"2025-05-21T10:17:30.000+0200","countdown":51},"vehicle":{"name":"U1","towards":"Leopoldau","direction":"H","platform":"1","richtungsId":"1","barrierFree":true,"foldingRamp":false,"realtimeSupported":true,"trafficjam":false,"type":"ptMetro","attributes":{},"linienId":301}},{"departureTime":{"timePlanned":"2025-05-21T10:21:15.000+0200","countdown":54},"vehicle":{"name":"U1","towards":"Leopoldau","direction":"H","platform":"1","richtungsId":"1","barrierFree":true,"foldingRamp":false,"realtimeSupported":true,"trafficjam":false,"type":"ptMetro","attributes":{},"linienId":301}},{"departureTime":{"timePlanned":"2025-05-21T10:25:00.000+0200","countdown":58},"vehicle":{"name":"U1","towards":"Leopoldau","direction":"H","platform":"1","richtungsId":"1","barrierFree":true,"foldingRamp":false,"realtimeSupported":true,"trafficjam":false,"type":"ptMetro","attributes":{},"linienId":301}},{"departureTime":{"timePlanned":"2025-05-21T10:28:45.000+0200","countdown":62},"vehicle":{"name":"U1","towards":"Leopoldau","direction":"H","platform":"1","richtungsId":"1","barrierFree":true,"foldingRamp":false,"realtimeSupported":true,"trafficjam":false,"type":"ptMetro","attributes":{},"linienId":301}},{"departureTime":{"timePlanned":"2025-05-21T10:32:30.000+0200","countdown":66},"vehicle":{"name":"U1","towards":"Leopoldau","direction":"H","platform":"1","richtungsId":"1","barrierFree":true,"foldingRamp":false,"realtimeSupported":true,"trafficjam":false,"type":"ptMetro","attributes":{},"linienId":301}},{"departureTime":{"timePlanned":"2025-05-21T10:36:15.000+0200","countdown":69},"vehicle":{"name":"U1","towards":"Leopoldau","direction":"H","platform":"1","richtungsId":"1","barrierFree":true,"foldingRamp":false,"realtimeSupported":true,"trafficjam":false,"type":"ptMetro","attributes":{},"linienId":301}}]},"type":"ptMetro","lineId":301}],"attributes":{}},{"locationStop":{"type":"Feature","geometry":{"type":"Point","coordinates":[16.391577,48.2191061]},"properties":{"name":"60201040","title":"Praterstern","municipality":"Wien","municipalityId":49000001,"type":"stop","coordName":"WGS84","gate":"2","attributes":{"rbl":4112}}},"lines":[{"name":"U1","towards":"OBERLAA       ","direction":"R","platform":"2","richtungsId":"2","barrierFree":true,"realtimeSupported":true,"trafficjam":false,"departures":{"departure":[{"departureTime":{"timePlanned":"2025-05-21T09:26:09.000+0200","timeReal":"2025-05-21T09:26:09.000+0200","countdown":0},"vehicle":{"name":"U1","towards":"OBERLAA       ","direction":"R","platform":"2","richtungsId":"2","barrierFree":true,"foldingRamp":true,"foldingRampType":"part","realtimeSupported":true,"trafficjam":false,"type":"ptMetro","attributes":{},"linienId":301}},{"departureTime":{"timePlanned":"2025-05-21T09:31:09.000+0200","timeReal":"2025-05-21T09:31:09.000+0200","countdown":5},"vehicle":{"name":"U1","towards":"ALAUDAGASSE","direction":"R","platform":"2","richtungsId":"2","barrierFree":true,"realtimeSupported":true,"trafficjam":false,"type":"ptMetro","attributes":{},"linienId":301}},{"departureTime":{"timePlanned":"2025-05-21T09:33:30.000+0200","countdown":7},"vehicle":{"name":"U1","towards":"Oberlaa","direction":"R","platform":"2","richtungsId":"2","barrierFree":true,"foldingRamp":false,"realtimeSupported":true,"trafficjam":false,"type":"ptMetro","attributes":{},"linienId":301}},{"departureTime":{"timePlanned":"2025-05-21T09:37:15.000+0200","countdown":10},"vehicle":{"name":"U1","towards":"Alaudagasse","direction":"R","platform":"2","richtungsId":"2","barrierFree":true,"foldingRamp":false,"realtimeSupported":true,"trafficjam":false,"type":"ptMetro","attributes":{},"linienId":301}},{"departureTime":{"timePlanned":"2025-05-21T09:41:00.000+0200","countdown":14},"vehicle":{"name":"U1","towards":"Oberlaa","direction":"R","platform":"2","richtungsId":"2","barrierFree":true,"foldingRamp":false,"realtimeSupported":true,"trafficjam":false,"type":"ptMetro","attributes":{},"linienId":301}},{"departureTime":{"timePlanned":"2025-05-21T09:44:45.000+0200","countdown":18},"vehicle":{"name":"U1","towards":"Alaudagasse","direction":"R","platform":"2","richtungsId":"2","barrierFree":true,"foldingRamp":false,"realtimeSupported":true,"trafficjam":false,"type":"ptMetro","attributes":{},"linienId":301}},{"departureTime":{"timePlanned":"2025-05-21T09:48:30.000+0200","countdown":22},"vehicle":{"name":"U1","towards":"Oberlaa","direction":"R","platform":"2","richtungsId":"2","barrierFree":true,"foldingRamp":false,"realtimeSupported":true,"trafficjam":false,"type":"ptMetro","attributes":{},"linienId":301}},{"departureTime":{"timePlanned":"2025-05-21T09:52:15.000+0200","countdown":25},"vehicle":{"name":"U1","towards":"Alaudagasse","direction":"R","platform":"2","richtungsId":"2","barrierFree":true,"foldingRamp":false,"realtimeSupported":true,"trafficjam":false,"type":"ptMetro","attributes":{},"linienId":301}},{"departureTime":{"timePlanned":"2025-05-21T09:56:00.000+0200","countdown":29},"vehicle":{"name":"U1","towards":"Oberlaa","direction":"R","platform":"2","richtungsId":"2","barrierFree":true,"foldingRamp":false,"realtimeSupported":true,"trafficjam":false,"type":"ptMetro","attributes":{},"linienId":301}},{"departureTime":{"timePlanned":"2025-05-21T09:59:45.000+0200","countdown":33},"vehicle":{"name":"U1","towards":"Alaudagasse","direction":"R","platform":"2","richtungsId":"2","barrierFree":true,"foldingRamp":false,"realtimeSupported":true,"trafficjam":false,"type":"ptMetro","attributes":{},"linienId":301}},{"departureTime":{"timePlanned":"2025-05-21T10:03:30.000+0200","countdown":37},"vehicle":{"name":"U1","towards":"Oberlaa","direction":"R","platform":"2","richtungsId":"2","barrierFree":true,"foldingRamp":false,"realtimeSupported":true,"trafficjam":false,"type":"ptMetro","attributes":{},"linienId":301}},{"departureTime":{"timePlanned":"2025-05-21T10:07:15.000+0200","countdown":40},"vehicle":{"name":"U1","towards":"Alaudagasse","direction":"R","platform":"2","richtungsId":"2","barrierFree":true,"foldingRamp":false,"realtimeSupported":true,"trafficjam":false,"type":"ptMetro","attributes":{},"linienId":301}},{"departureTime":{"timePlanned":"2025-05-21T10:11:00.000+0200","countdown":44},"vehicle":{"name":"U1","towards":"Oberlaa","direction":"R","platform":"2","richtungsId":"2","barrierFree":true,"foldingRamp":false,"realtimeSupported":true,"trafficjam":false,"type":"ptMetro","attributes":{},"linienId":301}},{"departureTime":{"timePlanned":"2025-05-21T10:14:45.000+0200","countdown":48},"vehicle":{"name":"U1","towards":"Alaudagasse","direction":"R","platform":"2","richtungsId":"2","barrierFree":true,"foldingRamp":false,"realtimeSupported":true,"trafficjam":false,"type":"ptMetro","attributes":{},"linienId":301}},{"departureTime":{"timePlanned":"2025-05-21T10:18:30.000+0200","countdown":52},"vehicle":{"name":"U1","towards":"Oberlaa","direction":"R","platform":"2","richtungsId":"2","barrierFree":true,"foldingRamp":false,"realtimeSupported":true,"trafficjam":false,"type":"ptMetro","attributes":{},"linienId":301}},{"departureTime":{"timePlanned":"2025-05-21T10:22:15.000+0200","countdown":55},"vehicle":{"name":"U1","towards":"Alaudagasse","direction":"R","platform":"2","richtungsId":"2","barrierFree":true,"foldingRamp":false,"realtimeSupported":true,"trafficjam":false,"type":"ptMetro","attributes":{},"linienId":301}},{"departureTime":{"timePlanned":"2025-05-21T10:26:00.000+0200","countdown":59},"vehicle":{"name":"U1","towards":"Oberlaa","direction":"R","platform":"2","richtungsId":"2","barrierFree":true,"foldingRamp":false,"realtimeSupported":true,"trafficjam":false,"type":"ptMetro","attributes":{},"linienId":301}},{"departureTime":{"timePlanned":"2025-05-21T10:29:45.000+0200","countdown":63},"vehicle":{"name":"U1","towards":"Alaudagasse","direction":"R","platform":"2","richtungsId":"2","barrierFree":true,"foldingRamp":false,"realtimeSupported":true,"trafficjam":false,"type":"ptMetro","attributes":{},"linienId":301}},{"departureTime":{"timePlanned":"2025-05-21T10:33:30.000+0200","countdown":67},"vehicle":{"name":"U1","towards":"Oberlaa","direction":"R","platform":"2","richtungsId":"2","barrierFree":true,"foldingRamp":false,"realtimeSupported":true,"trafficjam":false,"type":"ptMetro","attributes":{},"linienId":301}}]},"type":"ptMetro","lineId":301}],"attributes":{}},{"locationStop":{"type":"Feature","geometry":{"type":"Point","coordinates":[16.3933736,48.2186273]},"properties":{"name":"60201040","title":"Praterstern","municipality":"Wien","municipalityId":49000001,"type":"stop","coordName":"WGS84","gate":"1","attributes":{"rbl":4260}}},"lines":[{"name":"U2","towards":"KARLSPLATZ    ","direction":"H","platform":"1","richtungsId":"1","barrierFree":true,"realtimeSupported":true,"trafficjam":false,"departures":{"departure":[{"departureTime":{"timePlanned":"2025-05-21T09:26:09.000+0200","timeReal":"2025-05-21T09:26:09.000+0200","countdown":0},"vehicle":{"name":"U2","towards":"KARLSPLATZ    ","direction":"H","platform":"1","richtungsId":"1","barrierFree":true,"foldingRamp":true,"foldingRampType":"part","realtimeSupported":true,"trafficjam":false,"type":"ptMetro","attributes":{},"linienId":302}},{"departureTime":{"timePlanned":"2025-05-21T09:31:09.000+0200","timeReal":"2025-05-21T09:31:09.000+0200","countdown":5},"vehicle":{"name":"U2","towards":"KARLSPLATZ    ","direction":"H","platform":"1","richtungsId":"1","barrierFree":true,"foldingRamp":true,"foldingRampType":"part","realtimeSupported":true,"trafficjam":false,"type":"ptMetro","attributes":{},"linienId":302}},{"departureTime":{"timePlanned":"2025-05-21T09:35:00.000+0200","countdown":8},"vehicle":{"name":"U2","towards":"Karlsplatz","direction":"H","platform":"1","richtungsId":"1","barrierFree":true,"foldingRamp":false,"realtimeSupported":true,"trafficjam":false,"type":"ptMetro","attributes":{},"linienId":302}},{"departureTime":{"timePlanned":"2025-05-21T09:40:00.000+0200","countdown":13},"vehicle":{"name":"U2","towards":"Karlsplatz","direction":"H","platform":"1","richtungsId":"1","barrierFree":true,"foldingRamp":false,"realtimeSupported":true,"trafficjam":false,"type":"ptMetro","attributes":{},"linienId":302}},{"departureTime":{"timePlanned":"2025-05-21T09:45:00.000+0200","countdown":18},"vehicle":{"name":"U2","towards":"Karlsplatz","direction":"H","platform":"1","richtungsId":"1","barrierFree":true,"foldingRamp":false,"realtimeSupported":true,"trafficjam":false,"type":"ptMetro","attributes":{},"linienId":302}},{"departureTime":{"timePlanned":"2025-05-21T09:50:00.000+0200","countdown":23},"vehicle":{"name":"U2","towards":"Karlsplatz","direction":"H","platform":"1","richtungsId":"1","barrierFree":true,"foldingRamp":false,"realtimeSupported":true,"trafficjam":false,"type":"ptMetro","attributes":{},"linienId":302}},{"departureTime":{"timePlanned":"2025-05-21T09:55:00.000+0200","countdown":28},"vehicle":{"name":"U2","towards":"Karlsplatz","direction":"H","platform":"1","richtungsId":"1","barrierFree":true,"foldingRamp":false,"realtimeSupported":true,"trafficjam":false,"type":"ptMetro","attributes":{},"linienId":302}},{"departureTime":{"timePlanned":"2025-05-21T10:00:00.000+0200","countdown":33},"vehicle":{"name":"U2","towards":"Karlsplatz","direction":"H","platform":"1","richtungsId":"1","barrierFree":true,"foldingRamp":false,"realtimeSupported":true,"trafficjam":false,"type":"ptMetro","attributes":{},"linienId":302}},{"departureTime":{"timePlanned":"2025-05-21T10:05:00.000+0200","countdown":38},"vehicle":{"name":"U2","towards":"Karlsplatz","direction":"H","platform":"1","richtungsId":"1","barrierFree":true,"foldingRamp":false,"realtimeSupported":true,"trafficjam":false,"type":"ptMetro","attributes":{},"linienId":302}},{"departureTime":{"timePlanned":"2025-05-21T10:10:00.000+0200","countdown":43},"vehicle":{"name":"U2","towards":"Karlsplatz","direction":"H","platform":"1","richtungsId":"1","barrierFree":true,"foldingRamp":false,"realtimeSupported":true,"trafficjam":false,"type":"ptMetro","attributes":{},"linienId":302}},{"departureTime":{"timePlanned":"2025-05-21T10:15:00.000+0200","countdown":48},"vehicle":{"name":"U2","towards":"Karlsplatz","direction":"H","platform":"1","richtungsId":"1","barrierFree":true,"foldingRamp":false,"realtimeSupported":true,"trafficjam":false,"type":"ptMetro","attributes":{},"linienId":302}},{"departureTime":{"timePlanned":"2025-05-21T10:20:00.000+0200","countdown":53},"vehicle":{"name":"U2","towards":"Karlsplatz","direction":"H","platform":"1","richtungsId":"1","barrierFree":true,"foldingRamp":false,"realtimeSupported":true,"trafficjam":false,"type":"ptMetro","attributes":{},"linienId":302}},{"departureTime":{"timePlanned":"2025-05-21T10:25:00.000+0200","countdown":58},"vehicle":{"name":"U2","towards":"Karlsplatz","direction":"H","platform":"1","richtungsId":"1","barrierFree":true,"foldingRamp":false,"realtimeSupported":true,"trafficjam":false,"type":"ptMetro","attributes":{},"linienId":302}},{"departureTime":{"timePlanned":"2025-05-21T10:30:00.000+0200","countdown":63},"vehicle":{"name":"U2","towards":"Karlsplatz","direction":"H","platform":"1","richtungsId":"1","barrierFree":true,"foldingRamp":false,"realtimeSupported":true,"trafficjam":false,"type":"ptMetro","attributes":{},"linienId":302}},{"departureTime":{"timePlanned":"2025-05-21T10:35:00.000+0200","countdown":68},"vehicle":{"name":"U2","towards":"Karlsplatz","direction":"H","platform":"1","richtungsId":"1","barrierFree":true,"foldingRamp":false,"realtimeSupported":true,"trafficjam":false,"type":"ptMetro","attributes":{},"linienId":302}}]},"type":"ptMetro","lineId":302}],"attributes":{}},{"locationStop":{"type":"Feature","geometry":{"type":"Point","coordinates":[16.3933466,48.2185495]},"properties":{"name":"60201040","title":"Praterstern","municipality":"Wien","municipalityId":49000001,"type":"stop","coordName":"WGS84","gate":"2","attributes":{"rbl":4263}}},"lines":[{"name":"U2","towards":"SEESTADT      ","direction":"R","platform":"2","richtungsId":"2","barrierFree":true,"realtimeSupported":true,"trafficjam":false,"departures":{"departure":[{"departureTime":{"timePlanned":"2025-05-21T09:27:09.000+0200","timeReal":"2025-05-21T09:27:09.000+0200","countdown":1},"vehicle":{"name":"U2","towards":"SEESTADT      ","direction":"R","platform":"2","richtungsId":"2","barrierFree":true,"foldingRamp":true,"foldingRampType":"part","realtimeSupported":true,"trafficjam":false,"type":"ptMetro","attributes":{},"linienId":302}},{"departureTime":{"timePlanned":"2025-05-21T09:33:09.000+0200","timeReal":"2025-05-21T09:33:09.000+0200","countdown":7},"vehicle":{"name":"U2","towards":"ASPERNSTRASSE ","direction":"R","platform":"2","richtungsId":"2","barrierFree":true,"foldingRamp":true,"foldingRampType":"part","realtimeSupported":true,"trafficjam":false,"type":"ptMetro","attributes":{},"linienId":302}},{"departureTime":{"timePlanned":"2025-05-21T09:37:00.000+0200","countdown":10},"vehicle":{"name":"U2","towards":"Seestadt","direction":"R","platform":"2","richtungsId":"2","barrierFree":true,"foldingRamp":false,"realtimeSupported":true,"trafficjam":false,"type":"ptMetro","attributes":{},"linienId":302}},{"departureTime":{"timePlanned":"2025-05-21T09:42:00.000+0200","countdown":15},"vehicle":{"name":"U2","towards":"Aspernstraße","direction":"R","platform":"2","richtungsId":"2","barrierFree":true,"foldingRamp":false,"realtimeSupported":true,"trafficjam":false,"type":"ptMetro","attributes":{},"linienId":302}},{"departureTime":{"timePlanned":"2025-05-21T09:47:00.000+0200","countdown":20},"vehicle":{"name":"U2","towards":"Seestadt","direction":"R","platform":"2","richtungsId":"2","barrierFree":true,"foldingRamp":false,"realtimeSupported":true,"trafficjam":false,"type":"ptMetro","attributes":{},"linienId":302}},{"departureTime":{"timePlanned":"2025-05-21T09:52:00.000+0200","countdown":25},"vehicle":{"name":"U2","towards":"Aspernstraße","direction":"R","platform":"2","richtungsId":"2","barrierFree":true,"foldingRamp":false,"realtimeSupported":true,"trafficjam":false,"type":"ptMetro","attributes":{},"linienId":302}},{"departureTime":{"timePlanned":"2025-05-21T09:57:00.000+0200","countdown":30},"vehicle":{"name":"U2","towards":"Seestadt","direction":"R","platform":"2","richtungsId":"2","barrierFree":true,"foldingRamp":false,"realtimeSupported":true,"trafficjam":false,"type":"ptMetro","attributes":{},"linienId":302}},{"departureTime":{"timePlanned":"2025-05-21T10:02:00.000+0200","countdown":35},"vehicle":{"name":"U2","towards":"Aspernstraße","direction":"R","platform":"2","richtungsId":"2","barrierFree":true,"foldingRamp":false,"realtimeSupported":true,"trafficjam":false,"type":"ptMetro","attributes":{},"linienId":302}},{"departureTime":{"timePlanned":"2025-05-21T10:07:00.000+0200","countdown":40},"vehicle":{"name":"U2","towards":"Seestadt","direction":"R","platform":"2","richtungsId":"2","barrierFree":true,"foldingRamp":false,"realtimeSupported":true,"trafficjam":false,"type":"ptMetro","attributes":{},"linienId":302}},{"departureTime":{"timePlanned":"2025-05-21T10:12:00.000+0200","countdown":45},"vehicle":{"name":"U2","towards":"Aspernstraße","direction":"R","platform":"2","richtungsId":"2","barrierFree":true,"foldingRamp":false,"realtimeSupported":true,"trafficjam":false,"type":"ptMetro","attributes":{},"linienId":302}},{"departureTime":{"timePlanned":"2025-05-21T10:17:00.000+0200","countdown":50},"vehicle":{"name":"U2","towards":"Seestadt","direction":"R","platform":"2","richtungsId":"2","barrierFree":true,"foldingRamp":false,"realtimeSupported":true,"trafficjam":false,"type":"ptMetro","attributes":{},"linienId":302}},{"departureTime":{"timePlanned":"2025-05-21T10:22:00.000+0200","countdown":55},"vehicle":{"name":"U2","towards":"Aspernstraße","direction":"R","platform":"2","richtungsId":"2","barrierFree":true,"foldingRamp":false,"realtimeSupported":true,"trafficjam":false,"type":"ptMetro","attributes":{},"linienId":302}},{"departureTime":{"timePlanned":"2025-05-21T10:27:00.000+0200","countdown":60},"vehicle":{"name":"U2","towards":"Seestadt","direction":"R","platform":"2","richtungsId":"2","barrierFree":true,"foldingRamp":false,"realtimeSupported":true,"trafficjam":false,"type":"ptMetro","attributes":{},"linienId":302}},{"departureTime":{"timePlanned":"2025-05-21T10:32:00.000+0200","countdown":65},"vehicle":{"name":"U2","towards":"Aspernstraße","direction":"R","platform":"2","richtungsId":"2","barrierFree":true,"foldingRamp":false,"realtimeSupported":true,"trafficjam":false,"type":"ptMetro","attributes":{},"linienId":302}}]},"type":"ptMetro","lineId":302}],"attributes":{}}]},"message":{"value":"OK","messageCode":1,"serverTime":"2025-05-21T09:26:17.000+0200"}}